youmirror/__init__.py
youmirror/cli.py
youmirror/configurer.py
youmirror/core.py
youmirror/databaser.py
youmirror/downloader.py
youmirror/filer.py
youmirror/fixer.py
youmirror/parser.py
youmirror/printer.py
youmirror/pytube/__init__.py
youmirror/pytube/__main__.py
youmirror/pytube/captions.py
youmirror/pytube/cipher.py
youmirror/pytube/cli.py
youmirror/pytube/contrib/__init__.py
youmirror/pytube/contrib/channel.py
youmirror/pytube/contrib/playlist.py
youmirror/pytube/contrib/search.py
youmirror/pytube/exceptions.py
youmirror/pytube/extract.py
youmirror/pytube/helpers.py
youmirror/pytube/innertube.py
youmirror/pytube/itags.py
youmirror/pytube/metadata.py
youmirror/pytube/monostate.py
youmirror/pytube/parser.py
youmirror/pytube/query.py
youmirror/pytube/request.py
youmirror/pytube/streams.py
youmirror/pytube/version.py
youmirror/template.py
youmirror/tuber.py
youmirror-0.5.2.dist-info/entry_points.txt
youmirror-0.5.2.dist-info/LICENSE
youmirror-0.5.2.dist-info/WHEEL
youmirror-0.5.2.dist-info/METADATA
youmirror-0.5.2.dist-info/RECORD
