Metadata-Version: 2.1
Name: youmirror
Version: 0.5.2
Summary: Create a mirror filetree of your favorite youtube videos
Home-page: https://github.com/wkrettek/youmirror
License: MIT
Author: wkrettek
Author-email: warrenkrettek@gmail.com
Requires-Python: >=3.9,<4.0
Classifier: License :: OSI Approved :: MIT License
Classifier: Programming Language :: Python :: 3
Classifier: Programming Language :: Python :: 3.10
Classifier: Programming Language :: Python :: 3.9
Requires-Dist: sqlitedict (==2.0.0)
Requires-Dist: toml (>=0.10.2,<0.11.0)
Requires-Dist: typer (>=0.4.1,<0.5.0)
Project-URL: Repository, https://github.com/wkrettek/youmirror
